src/lock_arjun_apte/__init__.py
src/lock_arjun_apte/example.py
folder_locker_python-2023.25.1.dist-info/METADATA
folder_locker_python-2023.25.1.dist-info/WHEEL
folder_locker_python-2023.25.1.dist-info/licenses/LICENSE
folder_locker_python-2023.25.1.dist-info/RECORD
