Metadata-Version: 2.1
Name: folder_locker_python
Version: 2023.25.1
Summary: An easy python module to make a folder locker.
Project-URL: Homepage, https://github.com/pypa/sampleproject
Project-URL: Bug Tracker, https://github.com/pypa/sampleproject/issues
Author-email: Arjun Apte <arjunrohitapte@gmail.com>
License-File: LICENSE
Classifier: License :: OSI Approved :: MIT License
Classifier: Operating System :: OS Independent
Classifier: Programming Language :: Python :: 3
Requires-Python: >=3.7
